{
    "points": [
        {
            "time": 30.360000610351564,
            "angle": -1.25
        },
        {
            "time": 30.860000610351564,
            "angle": 12.289999961853028
        },
        {
            "time": 31.360000610351564,
            "angle": 10.319999694824219
        },
        {
            "time": 31.899999618530275,
            "angle": 5.789999961853027
        },
        {
            "time": 32.400001525878909,
            "angle": 1.5399999618530274
        },
        {
            "time": 32.900001525878909,
            "angle": 2.5899999141693117
        },
        {
            "time": 33.400001525878909,
            "angle": 2.390000104904175
        },
        {
            "time": 33.900001525878909,
            "angle": 16.540000915527345
        },
        {
            "time": 34.43000030517578,
            "angle": 15.34000015258789
        },
        {
            "time": 34.93000030517578,
            "angle": 10.329999923706055
        },
        {
            "time": 35.439998626708987,
            "angle": 8.770000457763672
        },
        {
            "time": 35.939998626708987,
            "angle": 8.510000228881836
        },
        {
            "time": 36.439998626708987,
            "angle": 8.619999885559082
        },
        {
            "time": 36.970001220703128,
            "angle": 4.849999904632568
        },
        {
            "time": 37.470001220703128,
            "angle": 4.440000057220459
        },
        {
            "time": 37.970001220703128,
            "angle": -4.0
        },
        {
            "time": 38.470001220703128,
            "angle": -8.489999771118164
        },
        {
            "time": 38.970001220703128,
            "angle": 0.33000001311302187
        },
        {
            "time": 39.5099983215332,
            "angle": -5.78000020980835
        },
        {
            "time": 40.0099983215332,
            "angle": 0.28999999165534975
        },
        {
            "time": 40.5099983215332,
            "angle": 0.6899999976158142
        },
        {
            "time": 41.0099983215332,
            "angle": -8.09000015258789
        },
        {
            "time": 41.5099983215332,
            "angle": -2.0799999237060549
        },
        {
            "time": 42.0099983215332,
            "angle": 8.890000343322754
        },
        {
            "time": 42.540000915527347,
            "angle": 7.670000076293945
        },
        {
            "time": 43.040000915527347,
            "angle": 3.8299999237060549
        },
        {
            "time": 43.540000915527347,
            "angle": -11.25
        },
        {
            "time": 44.040000915527347,
            "angle": -26.979999542236329
        },
        {
            "time": 44.58000183105469,
            "angle": -29.889999389648439
        },
        {
            "time": 45.08000183105469,
            "angle": -37.400001525878909
        },
        {
            "time": 45.58000183105469,
            "angle": -47.619998931884769
        },
        {
            "time": 46.08000183105469,
            "angle": -50.0
        },
        {
            "time": 46.58000183105469,
            "angle": -51.7400016784668
        },
        {
            "time": 47.08000183105469,
            "angle": -51.34000015258789
        },
        {
            "time": 47.58000183105469,
            "angle": -51.61000061035156
        },
        {
            "time": 48.08000183105469,
            "angle": -52.540000915527347
        },
        {
            "time": 48.619998931884769,
            "angle": -52.790000915527347
        },
        {
            "time": 49.119998931884769,
            "angle": -53.68000030517578
        },
        {
            "time": 49.619998931884769,
            "angle": -54.18000030517578
        },
        {
            "time": 50.150001525878909,
            "angle": -54.5099983215332
        },
        {
            "time": 50.650001525878909,
            "angle": -54.189998626708987
        },
        {
            "time": 51.150001525878909,
            "angle": -46.36000061035156
        },
        {
            "time": 51.650001525878909,
            "angle": -21.06999969482422
        },
        {
            "time": 52.150001525878909,
            "angle": -6.289999961853027
        },
        {
            "time": 52.650001525878909,
            "angle": 0.6100000143051148
        },
        {
            "time": 53.150001525878909,
            "angle": -0.8799999952316284
        },
        {
            "time": 53.689998626708987,
            "angle": -7.210000038146973
        },
        {
            "time": 54.189998626708987,
            "angle": -3.630000114440918
        },
        {
            "time": 54.720001220703128,
            "angle": 3.869999885559082
        },
        {
            "time": 55.220001220703128,
            "angle": 17.079999923706056
        },
        {
            "time": 55.720001220703128,
            "angle": 29.309999465942384
        },
        {
            "time": 56.220001220703128,
            "angle": 29.239999771118165
        },
        {
            "time": 56.720001220703128,
            "angle": 18.420000076293947
        },
        {
            "time": 57.2599983215332,
            "angle": 12.0
        },
        {
            "time": 57.7599983215332,
            "angle": 6.349999904632568
        },
        {
            "time": 58.2599983215332,
            "angle": -1.9299999475479127
        },
        {
            "time": 58.7599983215332,
            "angle": -5.449999809265137
        },
        {
            "time": 59.2599983215332,
            "angle": -6.699999809265137
        },
        {
            "time": 59.7599983215332,
            "angle": -5.5
        },
        {
            "time": 60.2599983215332,
            "angle": -0.9399999976158142
        },
        {
            "time": 60.790000915527347,
            "angle": -0.2800000011920929
        },
        {
            "time": 61.290000915527347,
            "angle": -5.96999979019165
        },
        {
            "time": 61.79999923706055,
            "angle": -14.890000343322754
        },
        {
            "time": 62.29999923706055,
            "angle": -18.010000228881837
        },
        {
            "time": 62.83000183105469,
            "angle": -19.950000762939454
        },
        {
            "time": 63.33000183105469,
            "angle": -19.59000015258789
        },
        {
            "time": 63.83000183105469,
            "angle": -20.209999084472658
        },
        {
            "time": 64.33000183105469,
            "angle": -18.489999771118165
        },
        {
            "time": 64.86000061035156,
            "angle": -15.890000343322754
        },
        {
            "time": 65.37000274658203,
            "angle": -1.649999976158142
        },
        {
            "time": 65.87000274658203,
            "angle": 2.890000104904175
        },
        {
            "time": 66.4000015258789,
            "angle": 4.46999979019165
        },
        {
            "time": 66.9000015258789,
            "angle": 4.909999847412109
        },
        {
            "time": 67.4000015258789,
            "angle": 3.009999990463257
        },
        {
            "time": 67.9000015258789,
            "angle": 2.059999942779541
        },
        {
            "time": 68.4000015258789,
            "angle": -5.380000114440918
        },
        {
            "time": 68.9000015258789,
            "angle": -5.480000019073486
        },
        {
            "time": 69.4000015258789,
            "angle": -2.930000066757202
        },
        {
            "time": 69.94000244140625,
            "angle": -7.050000190734863
        },
        {
            "time": 70.44000244140625,
            "angle": -3.819999933242798
        },
        {
            "time": 70.94000244140625,
            "angle": -15.680000305175782
        },
        {
            "time": 71.44000244140625,
            "angle": -27.770000457763673
        },
        {
            "time": 71.94000244140625,
            "angle": -34.59000015258789
        },
        {
            "time": 72.44000244140625,
            "angle": -35.18000030517578
        },
        {
            "time": 72.97000122070313,
            "angle": -34.7400016784668
        },
        {
            "time": 73.47000122070313,
            "angle": -31.520000457763673
        },
        {
            "time": 73.97000122070313,
            "angle": -10.569999694824219
        },
        {
            "time": 74.47000122070313,
            "angle": 1.2200000286102296
        },
        {
            "time": 75.01000213623047,
            "angle": 18.829999923706056
        },
        {
            "time": 75.51000213623047,
            "angle": 16.959999084472658
        },
        {
            "time": 76.01000213623047,
            "angle": 12.470000267028809
        },
        {
            "time": 76.51000213623047,
            "angle": 6.679999828338623
        },
        {
            "time": 77.01000213623047,
            "angle": 8.5600004196167
        },
        {
            "time": 77.51000213623047,
            "angle": 7.079999923706055
        },
        {
            "time": 78.04000091552735,
            "angle": 6.829999923706055
        },
        {
            "time": 78.55000305175781,
            "angle": 7.28000020980835
        },
        {
            "time": 79.05000305175781,
            "angle": 6.860000133514404
        },
        {
            "time": 79.55000305175781,
            "angle": -2.309999942779541
        },
        {
            "time": 80.08000183105469,
            "angle": -7.670000076293945
        },
        {
            "time": 80.58000183105469,
            "angle": -1.690000057220459
        },
        {
            "time": 81.08000183105469,
            "angle": -2.25
        },
        {
            "time": 81.58000183105469,
            "angle": 4.110000133514404
        },
        {
            "time": 82.12000274658203,
            "angle": 9.550000190734864
        },
        {
            "time": 82.62000274658203,
            "angle": 24.049999237060548
        },
        {
            "time": 83.12000274658203,
            "angle": 26.06999969482422
        },
        {
            "time": 83.62000274658203,
            "angle": 25.030000686645509
        },
        {
            "time": 84.1500015258789,
            "angle": 24.229999542236329
        },
        {
            "time": 84.6500015258789,
            "angle": 23.719999313354493
        },
        {
            "time": 85.1500015258789,
            "angle": 23.200000762939454
        },
        {
            "time": 85.6500015258789,
            "angle": 19.68000030517578
        },
        {
            "time": 86.1500015258789,
            "angle": 18.670000076293947
        },
        {
            "time": 86.6500015258789,
            "angle": 8.930000305175782
        },
        {
            "time": 87.1500015258789,
            "angle": 3.380000114440918
        },
        {
            "time": 87.69000244140625,
            "angle": 2.319999933242798
        },
        {
            "time": 88.19000244140625,
            "angle": 2.2200000286102297
        },
        {
            "time": 88.69000244140625,
            "angle": 2.359999895095825
        },
        {
            "time": 89.22000122070313,
            "angle": 2.7300000190734865
        },
        {
            "time": 89.72000122070313,
            "angle": 2.880000114440918
        },
        {
            "time": 90.22000122070313,
            "angle": 3.119999885559082
        },
        {
            "time": 90.72000122070313,
            "angle": 3.380000114440918
        },
        {
            "time": 91.22000122070313,
            "angle": 3.3299999237060549
        },
        {
            "time": 91.76000213623047,
            "angle": 3.2100000381469728
        },
        {
            "time": 92.26000213623047,
            "angle": 3.240000009536743
        },
        {
            "time": 92.76000213623047,
            "angle": 3.180000066757202
        },
        {
            "time": 93.26000213623047,
            "angle": 3.119999885559082
        },
        {
            "time": 93.76000213623047,
            "angle": 3.109999895095825
        },
        {
            "time": 94.29000091552735,
            "angle": 3.0899999141693117
        },
        {
            "time": 94.79000091552735,
            "angle": 3.0199999809265138
        },
        {
            "time": 95.30000305175781,
            "angle": 2.9200000762939455
        },
        {
            "time": 95.80000305175781,
            "angle": 2.9100000858306886
        },
        {
            "time": 96.33000183105469,
            "angle": 2.9200000762939455
        },
        {
            "time": 96.83000183105469,
            "angle": 3.380000114440918
        },
        {
            "time": 97.33000183105469,
            "angle": 2.4700000286102297
        },
        {
            "time": 97.83000183105469,
            "angle": 4.71999979019165
        },
        {
            "time": 98.33000183105469,
            "angle": 4.260000228881836
        },
        {
            "time": 98.87000274658203,
            "angle": 3.1700000762939455
        },
        {
            "time": 99.37000274658203,
            "angle": 3.440000057220459
        },
        {
            "time": 99.87000274658203,
            "angle": 2.009999990463257
        },
        {
            "time": 100.37000274658203,
            "angle": -4.690000057220459
        },
        {
            "time": 100.87000274658203,
            "angle": -2.859999895095825
        },
        {
            "time": 101.4000015258789,
            "angle": -2.0
        },
        {
            "time": 101.9000015258789,
            "angle": 2.0299999713897707
        },
        {
            "time": 102.4000015258789,
            "angle": 4.699999809265137
        },
        {
            "time": 102.9000015258789,
            "angle": -10.84000015258789
        },
        {
            "time": 103.44000244140625,
            "angle": -17.719999313354493
        },
        {
            "time": 103.94000244140625,
            "angle": -10.770000457763672
        },
        {
            "time": 104.44000244140625,
            "angle": -1.840000033378601
        },
        {
            "time": 104.97000122070313,
            "angle": 4.130000114440918
        },
        {
            "time": 105.47000122070313,
            "angle": 2.430000066757202
        },
        {
            "time": 105.97000122070313,
            "angle": -9.470000267028809
        },
        {
            "time": 106.47000122070313,
            "angle": -12.470000267028809
        },
        {
            "time": 107.01000213623047,
            "angle": -10.59000015258789
        },
        {
            "time": 107.51000213623047,
            "angle": -3.0399999618530275
        },
        {
            "time": 108.01000213623047,
            "angle": -12.859999656677246
        },
        {
            "time": 108.51000213623047,
            "angle": 13.300000190734864
        },
        {
            "time": 109.04000091552735,
            "angle": 18.969999313354493
        },
        {
            "time": 109.54000091552735,
            "angle": 20.510000228881837
        },
        {
            "time": 110.04000091552735,
            "angle": 0.05999999865889549
        },
        {
            "time": 110.58000183105469,
            "angle": -6.96999979019165
        },
        {
            "time": 111.08000183105469,
            "angle": -0.4399999976158142
        },
        {
            "time": 111.58000183105469,
            "angle": 3.890000104904175
        },
        {
            "time": 112.08000183105469,
            "angle": 9.789999961853028
        },
        {
            "time": 112.58000183105469,
            "angle": 3.619999885559082
        },
        {
            "time": 113.11000061035156,
            "angle": -2.509999990463257
        },
        {
            "time": 113.61000061035156,
            "angle": -1.0299999713897706
        },
        {
            "time": 114.1500015258789,
            "angle": 2.7300000190734865
        },
        {
            "time": 114.61000061035156,
            "angle": 3.0199999809265138
        },
        {
            "time": 115.12000274658203,
            "angle": 0.05000000074505806
        },
        {
            "time": 115.6500015258789,
            "angle": 2.440000057220459
        },
        {
            "time": 116.1500015258789,
            "angle": 2.2699999809265138
        },
        {
            "time": 116.6500015258789,
            "angle": 0.5799999833106995
        },
        {
            "time": 117.1500015258789,
            "angle": -16.950000762939454
        },
        {
            "time": 117.68000030517578,
            "angle": -23.219999313354493
        },
        {
            "time": 118.48999786376953,
            "angle": -1.6299999952316285
        },
        {
            "time": 119.0199966430664,
            "angle": 4.21999979019165
        },
        {
            "time": 119.5199966430664,
            "angle": 0.5099999904632568
        },
        {
            "time": 120.0199966430664,
            "angle": 0.09000000357627869
        },
        {
            "time": 120.5199966430664,
            "angle": 0.0
        },
        {
            "time": 121.0199966430664,
            "angle": -8.890000343322754
        },
        {
            "time": 121.55000305175781,
            "angle": -7.96999979019165
        },
        {
            "time": 122.05999755859375,
            "angle": -14.880000114440918
        },
        {
            "time": 122.55999755859375,
            "angle": -14.020000457763672
        },
        {
            "time": 123.08999633789063,
            "angle": -19.719999313354493
        },
        {
            "time": 123.58999633789063,
            "angle": -6.320000171661377
        },
        {
            "time": 124.08999633789063,
            "angle": 3.0999999046325685
        },
        {
            "time": 124.62000274658203,
            "angle": 4.510000228881836
        },
        {
            "time": 125.12000274658203,
            "angle": -8.25
        },
        {
            "time": 125.66000366210938,
            "angle": -4.849999904632568
        },
        {
            "time": 126.16000366210938,
            "angle": -9.649999618530274
        },
        {
            "time": 126.66000366210938,
            "angle": -13.609999656677246
        },
        {
            "time": 127.19000244140625,
            "angle": -12.399999618530274
        },
        {
            "time": 127.69000244140625,
            "angle": -1.0199999809265137
        },
        {
            "time": 128.22999572753907,
            "angle": 0.6899999976158142
        },
        {
            "time": 128.72999572753907,
            "angle": -1.2200000286102296
        },
        {
            "time": 129.22999572753907,
            "angle": -0.18000000715255738
        },
        {
            "time": 129.72999572753907,
            "angle": 0.23999999463558198
        },
        {
            "time": 130.22999572753907,
            "angle": 0.4300000071525574
        },
        {
            "time": 130.72999572753907,
            "angle": -0.4300000071525574
        },
        {
            "time": 131.22999572753907,
            "angle": -0.28999999165534975
        },
        {
            "time": 131.75999450683595,
            "angle": -0.6800000071525574
        },
        {
            "time": 132.27000427246095,
            "angle": -1.2000000476837159
        },
        {
            "time": 132.77000427246095,
            "angle": -1.4800000190734864
        },
        {
            "time": 133.27000427246095,
            "angle": -1.649999976158142
        },
        {
            "time": 133.8000030517578,
            "angle": -1.7599999904632569
        },
        {
            "time": 134.27000427246095,
            "angle": -1.9800000190734864
        },
        {
            "time": 134.77000427246095,
            "angle": -2.0999999046325685
        },
        {
            "time": 135.3000030517578,
            "angle": -2.259999990463257
        },
        {
            "time": 135.8000030517578,
            "angle": -2.390000104904175
        },
        {
            "time": 136.3000030517578,
            "angle": -0.5799999833106995
        },
        {
            "time": 136.8000030517578,
            "angle": 2.9100000858306886
        },
        {
            "time": 137.33999633789063,
            "angle": 3.5899999141693117
        },
        {
            "time": 137.83999633789063,
            "angle": 4.010000228881836
        },
        {
            "time": 138.33999633789063,
            "angle": 3.7200000286102297
        },
        {
            "time": 138.83999633789063,
            "angle": 2.4600000381469728
        },
        {
            "time": 139.33999633789063,
            "angle": 3.8399999141693117
        },
        {
            "time": 139.83999633789063,
            "angle": 7.690000057220459
        },
        {
            "time": 140.3699951171875,
            "angle": 2.8399999141693117
        },
        {
            "time": 140.8699951171875,
            "angle": -0.3700000047683716
        },
        {
            "time": 141.3699951171875,
            "angle": 1.0499999523162842
        },
        {
            "time": 141.8800048828125,
            "angle": -5.170000076293945
        },
        {
            "time": 142.41000366210938,
            "angle": 2.869999885559082
        },
        {
            "time": 142.91000366210938,
            "angle": 5.650000095367432
        },
        {
            "time": 143.41000366210938,
            "angle": 13.649999618530274
        },
        {
            "time": 143.91000366210938,
            "angle": -1.559999942779541
        },
        {
            "time": 144.41000366210938,
            "angle": 3.1700000762939455
        },
        {
            "time": 144.91000366210938,
            "angle": 7.579999923706055
        },
        {
            "time": 145.41000366210938,
            "angle": 12.170000076293946
        },
        {
            "time": 145.91000366210938,
            "angle": 11.869999885559082
        },
        {
            "time": 146.4499969482422,
            "angle": 11.069999694824219
        },
        {
            "time": 146.9499969482422,
            "angle": 10.680000305175782
        },
        {
            "time": 147.4499969482422,
            "angle": 10.579999923706055
        },
        {
            "time": 147.9499969482422,
            "angle": 10.449999809265137
        },
        {
            "time": 148.47999572753907,
            "angle": 10.470000267028809
        },
        {
            "time": 148.97999572753907,
            "angle": 10.5
        },
        {
            "time": 149.47999572753907,
            "angle": 10.489999771118164
        },
        {
            "time": 149.97999572753907,
            "angle": 10.479999542236329
        },
        {
            "time": 150.52000427246095,
            "angle": 10.430000305175782
        },
        {
            "time": 151.02000427246095,
            "angle": 10.350000381469727
        },
        {
            "time": 151.52000427246095,
            "angle": 10.050000190734864
        },
        {
            "time": 152.02000427246095,
            "angle": 9.970000267028809
        },
        {
            "time": 152.52000427246095,
            "angle": 9.859999656677246
        },
        {
            "time": 153.02000427246095,
            "angle": 9.800000190734864
        },
        {
            "time": 153.52000427246095,
            "angle": 9.760000228881836
        },
        {
            "time": 154.0500030517578,
            "angle": 9.619999885559082
        },
        {
            "time": 154.5500030517578,
            "angle": 9.630000114440918
        },
        {
            "time": 155.0500030517578,
            "angle": 9.489999771118164
        },
        {
            "time": 155.55999755859376,
            "angle": 7.409999847412109
        },
        {
            "time": 156.05999755859376,
            "angle": 5.079999923706055
        },
        {
            "time": 156.58999633789063,
            "angle": 2.5299999713897707
        },
        {
            "time": 157.08999633789063,
            "angle": -3.0399999618530275
        },
        {
            "time": 157.58999633789063,
            "angle": -0.75
        },
        {
            "time": 158.08999633789063,
            "angle": -1.4500000476837159
        },
        {
            "time": 158.58999633789063,
            "angle": 1.6299999952316285
        },
        {
            "time": 159.1300048828125,
            "angle": 10.649999618530274
        },
        {
            "time": 159.6300048828125,
            "angle": 1.4500000476837159
        },
        {
            "time": 160.16000366210938,
            "angle": 8.850000381469727
        },
        {
            "time": 160.66000366210938,
            "angle": 12.15999984741211
        },
        {
            "time": 161.16000366210938,
            "angle": 12.300000190734864
        },
        {
            "time": 161.66000366210938,
            "angle": 6.900000095367432
        },
        {
            "time": 162.16000366210938,
            "angle": 0.9399999976158142
        },
        {
            "time": 162.66000366210938,
            "angle": -4.610000133514404
        },
        {
            "time": 163.1999969482422,
            "angle": -4.389999866485596
        },
        {
            "time": 163.6999969482422,
            "angle": 2.4200000762939455
        },
        {
            "time": 164.1999969482422,
            "angle": 2.2200000286102297
        },
        {
            "time": 164.6999969482422,
            "angle": 5.099999904632568
        },
        {
            "time": 165.22999572753907,
            "angle": 5.010000228881836
        },
        {
            "time": 165.6999969482422,
            "angle": 7.360000133514404
        },
        {
            "time": 166.22999572753907,
            "angle": 7.380000114440918
        },
        {
            "time": 166.72999572753907,
            "angle": 6.239999771118164
        },
        {
            "time": 167.27000427246095,
            "angle": 1.6200000047683716
        },
        {
            "time": 167.77000427246095,
            "angle": 3.2300000190734865
        },
        {
            "time": 168.27000427246095,
            "angle": -0.3799999952316284
        },
        {
            "time": 168.77000427246095,
            "angle": 4.510000228881836
        },
        {
            "time": 169.27000427246095,
            "angle": 11.520000457763672
        },
        {
            "time": 169.77000427246095,
            "angle": 7.320000171661377
        },
        {
            "time": 170.27000427246095,
            "angle": 5.880000114440918
        },
        {
            "time": 170.77000427246095,
            "angle": 4.380000114440918
        },
        {
            "time": 171.27000427246095,
            "angle": -3.059999942779541
        },
        {
            "time": 171.77000427246095,
            "angle": -3.680000066757202
        },
        {
            "time": 172.30999755859376,
            "angle": -3.5999999046325685
        },
        {
            "time": 172.80999755859376,
            "angle": -3.4100000858306886
        },
        {
            "time": 173.30999755859376,
            "angle": -3.549999952316284
        },
        {
            "time": 173.83999633789063,
            "angle": -3.6500000953674318
        },
        {
            "time": 174.33999633789063,
            "angle": -3.690000057220459
        },
        {
            "time": 174.83999633789063,
            "angle": -3.9000000953674318
        },
        {
            "time": 175.33999633789063,
            "angle": -3.809999942779541
        },
        {
            "time": 175.83999633789063,
            "angle": -3.950000047683716
        },
        {
            "time": 176.3800048828125,
            "angle": -4.050000190734863
        },
        {
            "time": 176.8800048828125,
            "angle": -3.75
        },
        {
            "time": 177.3800048828125,
            "angle": -3.5799999237060549
        },
        {
            "time": 177.91000366210938,
            "angle": -3.369999885559082
        },
        {
            "time": 178.41000366210938,
            "angle": -3.119999885559082
        },
        {
            "time": 178.91000366210938,
            "angle": 1.5700000524520875
        },
        {
            "time": 179.41000366210938,
            "angle": 3.4700000286102297
        },
        {
            "time": 179.91000366210938,
            "angle": 3.4700000286102297
        },
        {
            "time": 180.41000366210938,
            "angle": 3.4600000381469728
        },
        {
            "time": 180.91000366210938,
            "angle": 10.529999732971192
        },
        {
            "time": 181.4499969482422,
            "angle": 12.5
        },
        {
            "time": 181.9499969482422,
            "angle": 13.220000267028809
        },
        {
            "time": 182.4499969482422,
            "angle": 12.569999694824219
        },
        {
            "time": 182.9499969482422,
            "angle": 12.390000343322754
        },
        {
            "time": 183.4499969482422,
            "angle": 11.9399995803833
        },
        {
            "time": 183.9499969482422,
            "angle": 11.760000228881836
        },
        {
            "time": 184.4499969482422,
            "angle": 11.680000305175782
        },
        {
            "time": 184.97999572753907,
            "angle": 11.890000343322754
        },
        {
            "time": 185.49000549316407,
            "angle": 11.489999771118164
        },
        {
            "time": 185.99000549316407,
            "angle": 11.239999771118164
        },
        {
            "time": 186.52000427246095,
            "angle": 11.170000076293946
        },
        {
            "time": 187.02000427246095,
            "angle": 10.989999771118164
        },
        {
            "time": 187.52000427246095,
            "angle": 10.869999885559082
        },
        {
            "time": 188.02000427246095,
            "angle": 10.850000381469727
        },
        {
            "time": 188.55999755859376,
            "angle": 10.680000305175782
        },
        {
            "time": 189.05999755859376,
            "angle": 10.449999809265137
        },
        {
            "time": 189.55999755859376,
            "angle": 8.119999885559082
        },
        {
            "time": 190.08999633789063,
            "angle": 7.75
        },
        {
            "time": 190.58999633789063,
            "angle": 10.199999809265137
        },
        {
            "time": 191.08999633789063,
            "angle": 12.130000114440918
        },
        {
            "time": 191.58999633789063,
            "angle": 9.84000015258789
        },
        {
            "time": 192.1300048828125,
            "angle": 8.520000457763672
        },
        {
            "time": 192.6300048828125,
            "angle": 10.869999885559082
        },
        {
            "time": 193.1300048828125,
            "angle": 15.949999809265137
        },
        {
            "time": 193.6300048828125,
            "angle": 15.470000267028809
        },
        {
            "time": 194.1300048828125,
            "angle": 11.859999656677246
        },
        {
            "time": 194.6300048828125,
            "angle": 6.510000228881836
        },
        {
            "time": 195.1300048828125,
            "angle": -3.549999952316284
        },
        {
            "time": 195.66000366210938,
            "angle": -10.829999923706055
        },
        {
            "time": 196.16000366210938,
            "angle": -11.25
        },
        {
            "time": 196.66000366210938,
            "angle": -13.399999618530274
        },
        {
            "time": 197.16000366210938,
            "angle": -15.550000190734864
        },
        {
            "time": 197.66000366210938,
            "angle": -15.40999984741211
        },
        {
            "time": 198.16000366210938,
            "angle": -16.549999237060548
        },
        {
            "time": 198.6999969482422,
            "angle": -14.529999732971192
        },
        {
            "time": 199.1999969482422,
            "angle": -4.059999942779541
        },
        {
            "time": 199.6999969482422,
            "angle": 4.599999904632568
        },
        {
            "time": 200.1999969482422,
            "angle": 5.289999961853027
        },
        {
            "time": 200.72999572753907,
            "angle": 2.5899999141693117
        },
        {
            "time": 201.22999572753907,
            "angle": 3.930000066757202
        },
        {
            "time": 201.72999572753907,
            "angle": 3.9700000286102297
        },
        {
            "time": 201.94000244140626,
            "angle": 4.260000228881836
        },
        {
            "time": 201.3000030517578,
            "angle": 2.0799999237060549
        },
        {
            "time": 201.8000030517578,
            "angle": -0.6399999856948853
        },
        {
            "time": 202.3000030517578,
            "angle": -23.940000534057618
        },
        {
            "time": 202.8000030517578,
            "angle": 0.7599999904632568
        },
        {
            "time": 203.1699981689453,
            "angle": 0.9900000095367432
        },
        {
            "time": 203.60000610351563,
            "angle": 1.9600000381469727
        },
        {
            "time": 204.27000427246095,
            "angle": 1.340000033378601
        },
        {
            "time": 204.8000030517578,
            "angle": 1.059999942779541
        },
        {
            "time": 205.1999969482422,
            "angle": 0.23999999463558198
        },
        {
            "time": 205.74000549316407,
            "angle": -0.800000011920929
        },
        {
            "time": 205.94000244140626,
            "angle": -0.699999988079071
        },
        {
            "time": 206.47000122070313,
            "angle": 12.199999809265137
        },
        {
            "time": 206.97000122070313,
            "angle": 12.380000114440918
        },
        {
            "time": 207.47000122070313,
            "angle": 10.289999961853028
        },
        {
            "time": 207.97000122070313,
            "angle": 7.159999847412109
        },
        {
            "time": 208.47000122070313,
            "angle": 6.610000133514404
        },
        {
            "time": 208.97999572753907,
            "angle": 5.980000019073486
        },
        {
            "time": 209.47999572753907,
            "angle": 6.360000133514404
        },
        {
            "time": 210.00999450683595,
            "angle": 6.170000076293945
        },
        {
            "time": 210.50999450683595,
            "angle": 9.670000076293946
        },
        {
            "time": 211.00999450683595,
            "angle": 8.970000267028809
        },
        {
            "time": 211.5399932861328,
            "angle": 9.930000305175782
        },
        {
            "time": 212.0500030517578,
            "angle": 9.90999984741211
        },
        {
            "time": 212.5500030517578,
            "angle": 9.510000228881836
        },
        {
            "time": 213.0500030517578,
            "angle": 6.230000019073486
        },
        {
            "time": 213.5500030517578,
            "angle": 4.96999979019165
        },
        {
            "time": 214.0500030517578,
            "angle": 0.05000000074505806
        },
        {
            "time": 214.5800018310547,
            "angle": -2.1700000762939455
        },
        {
            "time": 215.0800018310547,
            "angle": -0.1899999976158142
        },
        {
            "time": 215.5800018310547,
            "angle": 8.699999809265137
        },
        {
            "time": 216.1199951171875,
            "angle": 13.350000381469727
        },
        {
            "time": 216.6199951171875,
            "angle": 9.229999542236329
        }
    ],
    "videoName": "20180717_monkey cinema_focal manny_injected_360",
    "angleType": "Vertical",
    "videoDuration": 218.72,
    "userName": "Guidance_3",
    "fov": 108.0
}